{
  "entries": [
    {
      "path": "pomodoro2.pomodoro.csv",
      "dashboard": "work8",
      "skipOnMobile": false
    },
    {
      "path": "test2.habit.csv",
      "dashboard": "work8",
      "skipOnMobile": false
    },
    {
      "path": "my2.achievements.md",
      "dashboard": "new-dashboard",
      "skipOnMobile": false
    },
    {
      "path": "Whiteboard.tldraw.json",
      "dashboard": "default",
      "skipOnMobile": false
    },
    {
      "path": "events.events.csv",
      "dashboard": "default",
      "skipOnMobile": false
    },
    {
      "path": "my-feed.rss.json",
      "dashboard": "work8",
      "skipOnMobile": false
    }
  ],
  "files": {
    "selected": ".lifeos/.dashboard.config.json",
    "opened": [
      ".lifeos/.dashboard.config.json"
    ],
    "recentlyOpened": [
      ".lifeos/.dashboard.config.json",
      ".lifeos/events/new-event.lifosy-event.json",
      "my-lifosy-event.lifosy-event.json",
      ".lifeos/pois/test.poi.json",
      ".lifeos/.biolinks.json",
      "paris.poi.json"
    ]
  }
}